enum_extensions/__init__.py
enum_extensions/enum.py
enum_extensions/exceptions.py
enum_extension-1.0.1.dist-info/LICENSE
enum_extension-1.0.1.dist-info/METADATA
enum_extension-1.0.1.dist-info/WHEEL
enum_extension-1.0.1.dist-info/top_level.txt
enum_extension-1.0.1.dist-info/RECORD
