Metadata-Version: 2.1
Name: enum-extension
Version: 1.0.1
Summary: Python library that extends the functionality of the built-in enum module,
Author-email: MuhammadAli <usermalikhan@gmail.com>
License: MIT License
Project-URL: repository, https://github.com/m-ali-ubit/enum-extension
Project-URL: homepage, https://github.com/m-ali-ubit/enum-extension
Keywords: enum,extension,python,enhancements,utilities,advanced,capabilities
Classifier: Operating System :: OS Independent
Classifier: Topic :: Software Development :: Libraries :: Python Modules
Classifier: Programming Language :: Python :: 3
Classifier: Programming Language :: Python :: 3.6
Classifier: Programming Language :: Python :: 3.7
Classifier: Programming Language :: Python :: 3.8
Classifier: Programming Language :: Python :: 3.9
Classifier: Programming Language :: Python :: 3.10
Classifier: License :: OSI Approved :: MIT License
Requires-Python: >=3.6
License-File: LICENSE
